phammseqs/SequenceDB.py
phammseqs/__init__.py
phammseqs/__main__.py
phammseqs/cli.py
phammseqs/clustalo.py
phammseqs/mmseqs.py
phammseqs/multiprocess.py
phammseqs/pangenome.py
phammseqs/subprocess.py
phammseqs/fileio/__init__.py
phammseqs/fileio/fasta.py
phammseqs/fileio/genbank.py
phammseqs-1.0.4.dist-info/LICENSE
phammseqs-1.0.4.dist-info/METADATA
phammseqs-1.0.4.dist-info/WHEEL
phammseqs-1.0.4.dist-info/entry_points.txt
phammseqs-1.0.4.dist-info/top_level.txt
phammseqs-1.0.4.dist-info/RECORD
