Metadata-Version: 2.1
Name: phammseqs
Version: 1.0.4
Summary: Assort phage protein sequences into phamilies using MMseqs2
Home-page: https://github.com/chg60/PhaMMseqs.git
Author: Christian Gauthier
Author-email: chg60@pitt.edu
Project-URL: Source, https://github.com/chg60/PhaMMseqs.git
Classifier: Intended Audience :: Science/Research
Classifier: License :: OSI Approved :: GNU General Public License v3 (GPLv3)
Classifier: Operating System :: MacOS
Classifier: Operating System :: POSIX :: Linux
Classifier: Programming Language :: Python
Classifier: Programming Language :: Python :: 3
Classifier: Programming Language :: Python :: 3 :: Only
Classifier: Programming Language :: Python :: 3.7
Classifier: Programming Language :: Python :: 3.8
Classifier: Programming Language :: Python :: 3.9
Requires-Python: >=3.7
License-File: LICENSE
Requires-Dist: biopython
